facebook_bot
