Metadata-Version: 1.0
Name: python-facebook-bot
Version: 0.1.13
Summary: Using API to get Facebook Events by location, etc... with Python
Home-page: http://github.com/tudoanh/python-facebook-bot
Author: Do Anh Tu
Author-email: tu0703@gmail.com
License: MIT
Platform: UNKNOWN
